webuntis_fetcher/__init__.py
webuntis_fetcher/__main__.py
webuntis_fetcher/messages.py
webuntis_fetcher/starter.py
webuntis_fetcher/statistics.py
webuntis_fetcher/timetable.py
webuntis_fetcher-21.dist-info/licenses/LICENSE
webuntis_fetcher-21.dist-info/METADATA
webuntis_fetcher-21.dist-info/WHEEL
webuntis_fetcher-21.dist-info/entry_points.txt
webuntis_fetcher-21.dist-info/top_level.txt
webuntis_fetcher-21.dist-info/RECORD
