Metadata-Version: 2.4
Name: webuntis-fetcher
Version: 21
Summary: get school timetable data and messages from WebUntis
Author-email: Mathis Dirksen-Thedens <mail@zephyrsoft.org>
License-Expression: GPL-3.0-only
Project-URL: Homepage, https://github.com/mathisdt/webuntis-fetcher
Project-URL: Issues, https://github.com/mathisdt/webuntis-fetcher/issues
Keywords: webuntis,untis,school,timetable,message,lesson,period
Classifier: Programming Language :: Python :: 3
Classifier: Operating System :: OS Independent
Classifier: Environment :: Console
Classifier: Topic :: Education
Requires-Python: >=3.9
License-File: LICENSE
Requires-Dist: requests==2.32.5
Requires-Dist: beautifulsoup4==4.14.3
Requires-Dist: openpyxl==3.1.5
Dynamic: license-file
